{
  "name": "Learn Basic HTML by Building a Cat Photo App",
  "isUpcomingChange": true,
  "usesMultifileEditor": true,
  "hasEditableBoundaries": true,
  "dashedName": "learn-basic-html-by-building-a-cat-photo-app",
  "order": 2,
  "superBlock": "front-end-development",
  "challengeOrder": [
    {
      "id": "66731cd027ef3acb155669f5",
      "title": "Step 1"
    },
    {
      "id": "6690b9626a66f51257ae5a91",
      "title": "Step 2"
    },
    {
      "id": "6690b9a24f5b0f1300040c76",
      "title": "Step 3"
    },
    {
      "id": "6690ba16cf76f613b4e36197",
      "title": "Step 4"
    },
    {
      "id": "6690bb0b4062b114997f708a",
      "title": "Step 5"
    },
    {
      "id": "6690bd5ad96139157eedf697",
      "title": "Step 6"
    },
    {
      "id": "6690be42942f421648b119eb",
      "title": "Step 7"
    },
    {
      "id": "6690be902f051416f668962b",
      "title": "Step 8"
    },
    {
      "id": "6690bebfd5c918179ea4fd3a",
      "title": "Step 9"
    },
    {
      "id": "6690beec809b4f184cab6914",
      "title": "Step 10"
    }
  ],
  "helpCategory": "HTML-CSS"
}