{
  "isUpcomingChange": true,
  "dashedName": "lecture-understanding-websockets",
  "helpCategory": "Backend Development",
  "blockLayout": "challenge-list",
  "challengeOrder": [
    {
      "id": "6a1fefb066d06ad567fbeb43",
      "title": "What are WebSockets and How do They Differ from HTTP?"
    },
    {
      "id": "6a1ff130175dfa251ad1e1ca",
      "title": "What is the Pub/Sub Architecture?"
    },
    {
      "id": "6a215ebeb5896b637d7c3dc4",
      "title": "Working with WebSockets in Node.js"
    }
  ],
  "blockLabel": "lecture"
}
