{
  "name": "Build a Game Settings Panel",
  "isUpcomingChange": true,
  "dashedName": "workshop-game-settings-panel",
  "helpCategory": "HTML-CSS",
  "blockLayout": "challenge-grid",
  "challengeOrder": [
    { "id": "68e6a99a0fd7386fb66e156f", "title": "Step 1" },
    { "id": "68e9a3194160f8f5620ddf21", "title": "Step 2" },
    { "id": "68e9a3e82da294fb6395b647", "title": "Step 3" },
    { "id": "68e9a4a47d8a9802cba886b7", "title": "Step 4" },
    { "id": "68e9a54dd97fd9091e18acce", "title": "Step 5" },
    { "id": "68e9a6201e2efa142d62bfe1", "title": "Step 6" },
    { "id": "68e9a6bf1a74721a4e43e217", "title": "Step 7" },
    { "id": "68e9a73075dc26207320811a", "title": "Step 8" },
    { "id": "68e9a7bd60c971278d2d4ffc", "title": "Step 9" },
    { "id": "68e9a834dfef752dc35f6f90", "title": "Step 10" }
  ],
  "blockType": "workshop",
  "usesMultifileEditor": true,
  "hasEditableBoundaries": true
}
